wrapper/__init__.py
wrapper/wrapper.py
things3_wrapper-0.1.dist-info/LICENSE
things3_wrapper-0.1.dist-info/METADATA
things3_wrapper-0.1.dist-info/WHEEL
things3_wrapper-0.1.dist-info/top_level.txt
things3_wrapper-0.1.dist-info/RECORD
