Metadata-Version: 2.1
Name: things3-wrapper
Version: 0.1
Summary: Things 3 app python wrapper using URL scheme
Home-page: UNKNOWN
Author: jkkwoen
Author-email: jk.kwoen@gmail.com
License: MIT
Platform: UNKNOWN
